taisui/__init__.py
taisui/base/__init__.py
taisui/base/utils.py
taisui/base/functional/__init__.py
taisui/base/neuron/BaseNode.py
taisui/base/neuron/IFNode.py
taisui/base/neuron/LIFNode.py
taisui/base/neuron/__init__.py
taisui/base/surrogate/ATan.py
taisui/base/surrogate/BaseFunction.py
taisui/base/surrogate/Sigmoid.py
taisui/base/surrogate/__init__.py
taisui/datasets/__init__.py
taisui-0.1.1.dist-info/LICENSE
taisui-0.1.1.dist-info/METADATA
taisui-0.1.1.dist-info/WHEEL
taisui-0.1.1.dist-info/top_level.txt
taisui-0.1.1.dist-info/RECORD
