Metadata-Version: 2.1
Name: taisui
Version: 0.1.1
Summary: Third-generation Artificial Intelligence SNN Universal Implementation
Home-page: https://github.com/BIT-AETAS/taisui
Author: AETAS
Author-email: leiyunlin@bit.edu.cn, gaolanyu@bit.edu.cn
Classifier: Development Status :: 3 - Alpha
Classifier: Intended Audience :: Developers
Classifier: License :: OSI Approved :: Apache Software License
Classifier: Programming Language :: Python :: 3 :: Only
Classifier: Programming Language :: Python :: 3.6
Classifier: Programming Language :: Python :: 3.7
Classifier: Programming Language :: Python :: 3.8
Classifier: Programming Language :: Python :: 3.9
Classifier: Programming Language :: Python :: 3.10
Requires-Python: >=3.6,<=3.10
License-File: LICENSE
Requires-Dist: numpy
Requires-Dist: torch
Requires-Dist: torchvision
Requires-Dist: torchaudio
